{
  "kind": "collectionType",
  "collectionName": "pages",
  "info": {
    "singularName": "page",
    "pluralName": "pages",
    "displayName": "page",
    "description": ""
  },
  "options": {
    "draftAndPublish": true
  },
  "pluginOptions": {},
  "attributes": {
    "title": {
      "type": "string"
    },
    "slug": {
      "type": "string"
    },
    "seo": {
      "displayName": "seo",
      "type": "component",
      "repeatable": false,
      "component": "settings.seo"
    },
    "Blocks": {
      "type": "dynamiczone",
      "components": [
        "blocks.hero",
        "blocks.otzyvy"
      ]
    }
  }
}
